{
  "nodes": [
    {
      "name": "Geared population"
    },
    {
      "name": "Male"
    },
    {
      "name": "Female"
    },
    {
      "name": "Clerical and Administrative Workers"
    },
    {
      "name": "Community and Personal Service Workers"
    },
    {
      "name": "Labourers"
    },
    {
      "name": "Machinery operators and drivers"
    },
    {
      "name": "Managers"
    },
    {
      "name": "Other"
    },
    {
      "name": "Professionals"
    },
    {
      "name": "Sales workers"
    },
    {
      "name": "Technicians and Trades Workers"
    },
    {
      "name": "0-1k"
    },
    {
      "name": "1-3k"
    },
    {
      "name": "3-7k"
    },
    {
      "name": "Over 7k"
    },
    {
      "name": "0 - -1k"
    },
    {
      "name": "-1k - -3k"
    },
    {
      "name": "-3k - -7k"
    },
    {
      "name": "Over -7k"
    }
  ],
  "links": [
    {
      "source": 0,
      "target": 1,
      "value": 21354
    },
    {
      "source": 0,
      "target": 2,
      "value": 19242
    },
    {
      "source": 1,
      "target": 9,
      "value": 4084
    },
    {
      "source": 9,
      "target": 16,
      "value": 1844
    },
    {
      "source": 9,
      "target": 17,
      "value": 0
    },
    {
      "source": 9,
      "target": 18,
      "value": 0
    },
    {
      "source": 9,
      "target": 19,
      "value": 1128
    },
    {
      "source": 9,
      "target": 12,
      "value": 860
    },
    {
      "source": 9,
      "target": 13,
      "value": 225
    },
    {
      "source": 9,
      "target": 14,
      "value": 26
    },
    {
      "source": 9,
      "target": 15,
      "value": 1
    },
    {
      "source": 1,
      "target": 8,
      "value": 6157
    },
    {
      "source": 8,
      "target": 16,
      "value": 1875
    },
    {
      "source": 8,
      "target": 17,
      "value": 0
    },
    {
      "source": 8,
      "target": 18,
      "value": 0
    },
    {
      "source": 8,
      "target": 19,
      "value": 762
    },
    {
      "source": 8,
      "target": 12,
      "value": 2305
    },
    {
      "source": 8,
      "target": 13,
      "value": 966
    },
    {
      "source": 8,
      "target": 14,
      "value": 227
    },
    {
      "source": 8,
      "target": 15,
      "value": 22
    },
    {
      "source": 1,
      "target": 10,
      "value": 549
    },
    {
      "source": 10,
      "target": 16,
      "value": 281
    },
    {
      "source": 10,
      "target": 17,
      "value": 0
    },
    {
      "source": 10,
      "target": 18,
      "value": 0
    },
    {
      "source": 10,
      "target": 19,
      "value": 98
    },
    {
      "source": 10,
      "target": 12,
      "value": 136
    },
    {
      "source": 10,
      "target": 13,
      "value": 26
    },
    {
      "source": 10,
      "target": 14,
      "value": 8
    },
    {
      "source": 10,
      "target": 15,
      "value": 0
    },
    {
      "source": 1,
      "target": 5,
      "value": 936
    },
    {
      "source": 5,
      "target": 16,
      "value": 489
    },
    {
      "source": 5,
      "target": 17,
      "value": 0
    },
    {
      "source": 5,
      "target": 18,
      "value": 0
    },
    {
      "source": 5,
      "target": 19,
      "value": 145
    },
    {
      "source": 5,
      "target": 12,
      "value": 249
    },
    {
      "source": 5,
      "target": 13,
      "value": 49
    },
    {
      "source": 5,
      "target": 14,
      "value": 4
    },
    {
      "source": 5,
      "target": 15,
      "value": 0
    },
    {
      "source": 1,
      "target": 3,
      "value": 1040
    },
    {
      "source": 3,
      "target": 16,
      "value": 516
    },
    {
      "source": 3,
      "target": 17,
      "value": 0
    },
    {
      "source": 3,
      "target": 18,
      "value": 0
    },
    {
      "source": 3,
      "target": 19,
      "value": 252
    },
    {
      "source": 3,
      "target": 12,
      "value": 212
    },
    {
      "source": 3,
      "target": 13,
      "value": 59
    },
    {
      "source": 3,
      "target": 14,
      "value": 1
    },
    {
      "source": 3,
      "target": 15,
      "value": 0
    },
    {
      "source": 1,
      "target": 7,
      "value": 3610
    },
    {
      "source": 7,
      "target": 16,
      "value": 1596
    },
    {
      "source": 7,
      "target": 17,
      "value": 0
    },
    {
      "source": 7,
      "target": 18,
      "value": 0
    },
    {
      "source": 7,
      "target": 19,
      "value": 958
    },
    {
      "source": 7,
      "target": 12,
      "value": 781
    },
    {
      "source": 7,
      "target": 13,
      "value": 221
    },
    {
      "source": 7,
      "target": 14,
      "value": 50
    },
    {
      "source": 7,
      "target": 15,
      "value": 4
    },
    {
      "source": 1,
      "target": 6,
      "value": 1304
    },
    {
      "source": 6,
      "target": 16,
      "value": 702
    },
    {
      "source": 6,
      "target": 17,
      "value": 0
    },
    {
      "source": 6,
      "target": 18,
      "value": 0
    },
    {
      "source": 6,
      "target": 19,
      "value": 265
    },
    {
      "source": 6,
      "target": 12,
      "value": 298
    },
    {
      "source": 6,
      "target": 13,
      "value": 36
    },
    {
      "source": 6,
      "target": 14,
      "value": 3
    },
    {
      "source": 6,
      "target": 15,
      "value": 0
    },
    {
      "source": 1,
      "target": 11,
      "value": 2910
    },
    {
      "source": 11,
      "target": 16,
      "value": 1560
    },
    {
      "source": 11,
      "target": 17,
      "value": 0
    },
    {
      "source": 11,
      "target": 18,
      "value": 0
    },
    {
      "source": 11,
      "target": 19,
      "value": 589
    },
    {
      "source": 11,
      "target": 12,
      "value": 612
    },
    {
      "source": 11,
      "target": 13,
      "value": 130
    },
    {
      "source": 11,
      "target": 14,
      "value": 19
    },
    {
      "source": 11,
      "target": 15,
      "value": 0
    },
    {
      "source": 1,
      "target": 4,
      "value": 764
    },
    {
      "source": 4,
      "target": 16,
      "value": 428
    },
    {
      "source": 4,
      "target": 17,
      "value": 0
    },
    {
      "source": 4,
      "target": 18,
      "value": 0
    },
    {
      "source": 4,
      "target": 19,
      "value": 162
    },
    {
      "source": 4,
      "target": 12,
      "value": 138
    },
    {
      "source": 4,
      "target": 13,
      "value": 30
    },
    {
      "source": 4,
      "target": 14,
      "value": 6
    },
    {
      "source": 4,
      "target": 15,
      "value": 0
    },
    {
      "source": 2,
      "target": 8,
      "value": 5970
    },
    {
      "source": 8,
      "target": 16,
      "value": 1832
    },
    {
      "source": 8,
      "target": 17,
      "value": 0
    },
    {
      "source": 8,
      "target": 18,
      "value": 0
    },
    {
      "source": 8,
      "target": 19,
      "value": 461
    },
    {
      "source": 8,
      "target": 12,
      "value": 2300
    },
    {
      "source": 8,
      "target": 13,
      "value": 1084
    },
    {
      "source": 8,
      "target": 14,
      "value": 273
    },
    {
      "source": 8,
      "target": 15,
      "value": 20
    },
    {
      "source": 2,
      "target": 9,
      "value": 4668
    },
    {
      "source": 9,
      "target": 16,
      "value": 2427
    },
    {
      "source": 9,
      "target": 17,
      "value": 0
    },
    {
      "source": 9,
      "target": 18,
      "value": 0
    },
    {
      "source": 9,
      "target": 19,
      "value": 787
    },
    {
      "source": 9,
      "target": 12,
      "value": 1179
    },
    {
      "source": 9,
      "target": 13,
      "value": 244
    },
    {
      "source": 9,
      "target": 14,
      "value": 30
    },
    {
      "source": 9,
      "target": 15,
      "value": 1
    },
    {
      "source": 2,
      "target": 3,
      "value": 3796
    },
    {
      "source": 3,
      "target": 16,
      "value": 2027
    },
    {
      "source": 3,
      "target": 17,
      "value": 0
    },
    {
      "source": 3,
      "target": 18,
      "value": 0
    },
    {
      "source": 3,
      "target": 19,
      "value": 469
    },
    {
      "source": 3,
      "target": 12,
      "value": 1031
    },
    {
      "source": 3,
      "target": 13,
      "value": 228
    },
    {
      "source": 3,
      "target": 14,
      "value": 40
    },
    {
      "source": 3,
      "target": 15,
      "value": 1
    },
    {
      "source": 2,
      "target": 7,
      "value": 1949
    },
    {
      "source": 7,
      "target": 16,
      "value": 992
    },
    {
      "source": 7,
      "target": 17,
      "value": 0
    },
    {
      "source": 7,
      "target": 18,
      "value": 0
    },
    {
      "source": 7,
      "target": 19,
      "value": 387
    },
    {
      "source": 7,
      "target": 12,
      "value": 424
    },
    {
      "source": 7,
      "target": 13,
      "value": 124
    },
    {
      "source": 7,
      "target": 14,
      "value": 22
    },
    {
      "source": 7,
      "target": 15,
      "value": 0
    },
    {
      "source": 2,
      "target": 4,
      "value": 1192
    },
    {
      "source": 4,
      "target": 16,
      "value": 695
    },
    {
      "source": 4,
      "target": 17,
      "value": 0
    },
    {
      "source": 4,
      "target": 18,
      "value": 0
    },
    {
      "source": 4,
      "target": 19,
      "value": 145
    },
    {
      "source": 4,
      "target": 12,
      "value": 298
    },
    {
      "source": 4,
      "target": 13,
      "value": 47
    },
    {
      "source": 4,
      "target": 14,
      "value": 7
    },
    {
      "source": 4,
      "target": 15,
      "value": 0
    },
    {
      "source": 2,
      "target": 5,
      "value": 408
    },
    {
      "source": 5,
      "target": 16,
      "value": 226
    },
    {
      "source": 5,
      "target": 17,
      "value": 0
    },
    {
      "source": 5,
      "target": 18,
      "value": 0
    },
    {
      "source": 5,
      "target": 19,
      "value": 31
    },
    {
      "source": 5,
      "target": 12,
      "value": 133
    },
    {
      "source": 5,
      "target": 13,
      "value": 14
    },
    {
      "source": 5,
      "target": 14,
      "value": 4
    },
    {
      "source": 5,
      "target": 15,
      "value": 0
    },
    {
      "source": 2,
      "target": 11,
      "value": 325
    },
    {
      "source": 11,
      "target": 16,
      "value": 189
    },
    {
      "source": 11,
      "target": 17,
      "value": 0
    },
    {
      "source": 11,
      "target": 18,
      "value": 0
    },
    {
      "source": 11,
      "target": 19,
      "value": 35
    },
    {
      "source": 11,
      "target": 12,
      "value": 83
    },
    {
      "source": 11,
      "target": 13,
      "value": 14
    },
    {
      "source": 11,
      "target": 14,
      "value": 4
    },
    {
      "source": 11,
      "target": 15,
      "value": 0
    },
    {
      "source": 2,
      "target": 10,
      "value": 849
    },
    {
      "source": 10,
      "target": 16,
      "value": 470
    },
    {
      "source": 10,
      "target": 17,
      "value": 0
    },
    {
      "source": 10,
      "target": 18,
      "value": 0
    },
    {
      "source": 10,
      "target": 19,
      "value": 80
    },
    {
      "source": 10,
      "target": 12,
      "value": 257
    },
    {
      "source": 10,
      "target": 13,
      "value": 40
    },
    {
      "source": 10,
      "target": 14,
      "value": 2
    },
    {
      "source": 10,
      "target": 15,
      "value": 0
    },
    {
      "source": 2,
      "target": 6,
      "value": 85
    },
    {
      "source": 6,
      "target": 16,
      "value": 45
    },
    {
      "source": 6,
      "target": 17,
      "value": 0
    },
    {
      "source": 6,
      "target": 18,
      "value": 0
    },
    {
      "source": 6,
      "target": 19,
      "value": 17
    },
    {
      "source": 6,
      "target": 12,
      "value": 22
    },
    {
      "source": 6,
      "target": 13,
      "value": 0
    },
    {
      "source": 6,
      "target": 14,
      "value": 1
    },
    {
      "source": 6,
      "target": 15,
      "value": 0
    }
  ]
}
